{
  "Versions": {
    "mot": 698,
    "motlist": 751,
    "rdd": 2037022,
    "user": 2,
    "jmap": 19,
    "scn": 20,
    "mdf2": 40,
    "mesh": 240423143,
    "sdftex": 858718212,
    "tex": 760230703,
    "mmtr": 240112003,
    "mcol": 24021,
    "ainvm": 30,
    "coco": 9,
    "fol": 3,
    "rmesh": 26013,
    "rcol": 27,
    "mpci": 12,
    "pfb": 17,
    "psop": 3,
    "ucurve": 63,
    "motfsm2": 43,
    "ccbk": 3,
    "ikleg2": 24,
    "iklookat2": 26,
    "motbank": 3,
    "retargetrig": 8,
    "rbs": 2037,
    "aiwayp": 9,
    "ikls": 28,
    "jcns": 24,
    "skeleton": 6,
    "uvar": 3,
    "ikbodyrig": 3,
    "ikhd": 5,
    "fbik": 6,
    "ikmulti": 4,
    "iktrain2": 1,
    "rtex": 5,
    "amix": 2,
    "vsrc": 18,
    "clip": 62,
    "chain": 54,
    "ncf": 10,
    "fbxskel": 6,
    "gpbf": 2,
    "chain2": 4,
    "gpuc": 231011972,
    "clsm": 17,
    "clsp": 3,
    "wrap": 231025828,
    "sfur": 5,
    "cfil": 7,
    "cmat": 3,
    "cdef": 7,
    "finf": 2,
    "def": 6,
    "gcp": 2,
    "gsty": 4,
    "gcf": 27,
    "rcf": 2,
    "rtmr": 6,
    "sss": 4,
    "lod": 3,
    "terr": 24008,
    "hf": 4,
    "chf": 2,
    "gml": 858718217,
    "gtl": 858718223,
    "grnd": 858720015,
    "stmesh": 231011879,
    "abcmesh": 12,
    "mcamlist": 22,
    "tmlfsm2": 41062003,
    "uvs": 8,
    "efx": 4064419,
    "gui": 620035,
    "oft": 1,
    "fslt": 4,
    "ift": 7,
    "ocioc": 1000342933,
    "star": 3,
    "msg": 22,
    "mov": 1,
    "aimapattr": 46,
    "ainvmmgr": 8,
    "aiwaypmgr": 8,
    "swms": 1,
    "sbnk": 1,
    "spck": 1,
    "sdf": 240112003,
    "lprb": 6,
    "prb": 9,
    "rcfg": 10,
    "vsdf": 240112006,
    "vsdflist": 1,
    "efcsv": 1,
    "tml": 62002,
    "lfa": 4,
    "fxct": 4,
    "eem": 0
  },
  "Info": {
    "mot": {
      "Locales": [],
      "Type": "Motion",
      "Version": 698,
      "CanNotHaveX64": true,
      "CanNotHaveLang": true
    },
    "motlist": {
      "Locales": [],
      "Type": "MotionList",
      "Version": 751,
      "CanNotHaveX64": true,
      "CanNotHaveLang": true
    },
    "rdd": {
      "Locales": [],
      "Type": "Ragdoll",
      "Version": 2037022,
      "CanNotHaveX64": true,
      "CanNotHaveLang": true
    },
    "user": {
      "Locales": [],
      "Type": "UserData",
      "Version": 2,
      "CanHaveX64": true,
      "CanNotHaveX64": true,
      "CanNotHaveLang": true
    },
    "jmap": {
      "Locales": [],
      "Type": "JointMap",
      "Version": 19,
      "CanNotHaveX64": true,
      "CanNotHaveLang": true
    },
    "scn": {
      "Locales": [],
      "Type": "Scene",
      "Version": 20,
      "CanNotHaveX64": true,
      "CanNotHaveLang": true
    },
    "mdf2": {
      "Locales": [],
      "Type": "MaterialDefinition",
      "Version": 40,
      "CanNotHaveX64": true,
      "CanNotHaveLang": true
    },
    "mesh": {
      "Locales": [],
      "Type": "Mesh",
      "Version": 240423143,
      "CanNotHaveX64": true,
      "CanNotHaveLang": true
    },
    "sdftex": {
      "Locales": [],
      "Type": "SDFTexture",
      "Version": 858718212,
      "CanNotHaveX64": true,
      "CanNotHaveLang": true
    },
    "tex": {
      "Locales": [],
      "Type": "Texture",
      "Version": 760230703,
      "CanHaveX64": true,
      "CanNotHaveX64": true,
      "CanNotHaveLang": true
    },
    "mmtr": {
      "Locales": [],
      "Type": "MasterMaterial",
      "Version": 240112003,
      "CanNotHaveX64": true,
      "CanNotHaveLang": true
    },
    "mcol": {
      "Locales": [],
      "Type": "CollisionMesh",
      "Version": 24021,
      "CanNotHaveX64": true,
      "CanNotHaveLang": true
    },
    "ainvm": {
      "Locales": [],
      "Type": "AIMap",
      "Version": 30,
      "CanNotHaveX64": true,
      "CanNotHaveLang": true
    },
    "coco": {
      "Locales": [],
      "Type": "CompositeCollision",
      "Version": 9,
      "CanNotHaveX64": true,
      "CanNotHaveLang": true
    },
    "fol": {
      "Locales": [],
      "Type": "Foliage",
      "Version": 3,
      "CanNotHaveX64": true,
      "CanNotHaveLang": true
    },
    "rmesh": {
      "Locales": [],
      "Type": "RigidBodyMesh",
      "Version": 26013,
      "CanNotHaveX64": true,
      "CanNotHaveLang": true
    },
    "rcol": {
      "Locales": [],
      "Type": "RequestSetCollider",
      "Version": 27,
      "CanNotHaveX64": true,
      "CanNotHaveLang": true
    },
    "mpci": {
      "Locales": [],
      "Type": "MaterialPointCloud",
      "Version": 12,
      "CanNotHaveX64": true,
      "CanNotHaveLang": true
    },
    "pfb": {
      "Locales": [],
      "Type": "Prefab",
      "Version": 17,
      "CanHaveX64": true,
      "CanNotHaveX64": true,
      "CanNotHaveLang": true
    },
    "psop": {
      "Locales": [],
      "Type": "PSOPatch",
      "Version": 3,
      "CanNotHaveX64": true,
      "CanNotHaveLang": true
    },
    "ucurve": {
      "Locales": [],
      "Type": "UserCurve",
      "Version": 63,
      "CanNotHaveX64": true,
      "CanNotHaveLang": true
    },
    "motfsm2": {
      "Locales": [],
      "Type": "MotionFsm2",
      "Version": 43,
      "CanNotHaveX64": true,
      "CanNotHaveLang": true
    },
    "ccbk": {
      "Locales": [],
      "Type": "CharacterColliderBank",
      "Version": 3,
      "CanNotHaveX64": true,
      "CanNotHaveLang": true
    },
    "ikleg2": {
      "Locales": [],
      "Type": "IkLeg2",
      "Version": 24,
      "CanNotHaveX64": true,
      "CanNotHaveLang": true
    },
    "iklookat2": {
      "Locales": [],
      "Type": "IkLookAt2",
      "Version": 26,
      "CanNotHaveX64": true,
      "CanNotHaveLang": true
    },
    "motbank": {
      "Locales": [],
      "Type": "MotionBank",
      "Version": 3,
      "CanNotHaveX64": true,
      "CanNotHaveLang": true
    },
    "retargetrig": {
      "Locales": [],
      "Type": "RetargetRig",
      "Version": 8,
      "CanNotHaveX64": true,
      "CanNotHaveLang": true
    },
    "rbs": {
      "Locales": [],
      "Type": "RigidBodySet",
      "Version": 2037,
      "CanNotHaveX64": true,
      "CanNotHaveLang": true
    },
    "aiwayp": {
      "Locales": [],
      "Type": "AIMap",
      "Version": 9,
      "CanNotHaveX64": true,
      "CanNotHaveLang": true
    },
    "ikls": {
      "Locales": [],
      "Type": "IkLegSpine",
      "Version": 28,
      "CanNotHaveX64": true,
      "CanNotHaveLang": true
    },
    "jcns": {
      "Locales": [],
      "Type": "JointConstraints",
      "Version": 24,
      "CanNotHaveX64": true,
      "CanNotHaveLang": true
    },
    "skeleton": {
      "Locales": [],
      "Type": "Skeleton",
      "Version": 6,
      "CanNotHaveX64": true,
      "CanNotHaveLang": true
    },
    "uvar": {
      "Locales": [],
      "Type": "UserVariables",
      "Version": 3,
      "CanNotHaveX64": true,
      "CanNotHaveLang": true
    },
    "ikbodyrig": {
      "Locales": [],
      "Type": "IkBodyRig",
      "Version": 3,
      "CanNotHaveX64": true,
      "CanNotHaveLang": true
    },
    "ikhd": {
      "Locales": [],
      "Type": "IkHand2",
      "Version": 5,
      "CanNotHaveX64": true,
      "CanNotHaveLang": true
    },
    "fbik": {
      "Locales": [],
      "Type": "FullBodyIKRig",
      "Version": 6,
      "CanNotHaveX64": true,
      "CanNotHaveLang": true
    },
    "ikmulti": {
      "Locales": [],
      "Type": "IkMultiBone",
      "Version": 4,
      "CanNotHaveX64": true,
      "CanNotHaveLang": true
    },
    "iktrain2": {
      "Locales": [],
      "Type": "IkTrain2",
      "Version": 1,
      "CanNotHaveX64": true,
      "CanNotHaveLang": true
    },
    "rtex": {
      "Locales": [],
      "Type": "RenderTexture",
      "Version": 5,
      "CanNotHaveX64": true,
      "CanNotHaveLang": true
    },
    "amix": {
      "Locales": [],
      "Type": "AudioMixer",
      "Version": 2,
      "CanNotHaveX64": true,
      "CanNotHaveLang": true
    },
    "vsrc": {
      "Locales": [],
      "Type": "VibrationSource",
      "Version": 18,
      "CanNotHaveX64": true,
      "CanNotHaveLang": true
    },
    "clip": {
      "Locales": [],
      "Type": "Clip",
      "Version": 62,
      "CanNotHaveX64": true,
      "CanNotHaveLang": true
    },
    "chain": {
      "Locales": [],
      "Type": "Chain",
      "Version": 54,
      "CanNotHaveX64": true,
      "CanNotHaveLang": true
    },
    "ncf": {
      "Locales": [],
      "Type": "NetworkConfig",
      "Version": 10,
      "CanNotHaveX64": true,
      "CanNotHaveLang": true
    },
    "fbxskel": {
      "Locales": [],
      "Type": "FbxSkeleton",
      "Version": 6,
      "CanNotHaveX64": true,
      "CanNotHaveLang": true
    },
    "gpbf": {
      "Locales": [],
      "Type": "ByteBuffer",
      "Version": 2,
      "CanNotHaveX64": true,
      "CanNotHaveLang": true
    },
    "chain2": {
      "Locales": [],
      "Type": "Chain2",
      "Version": 4,
      "CanNotHaveX64": true,
      "CanNotHaveLang": true
    },
    "gpuc": {
      "Locales": [],
      "Type": "GpuCloth",
      "Version": 231011972,
      "CanNotHaveX64": true,
      "CanNotHaveLang": true
    },
    "clsm": {
      "Locales": [],
      "Type": "CollisionSkinningMesh",
      "Version": 17,
      "CanNotHaveX64": true,
      "CanNotHaveLang": true
    },
    "clsp": {
      "Locales": [],
      "Type": "CollisionShapePreset",
      "Version": 3,
      "CanNotHaveX64": true,
      "CanNotHaveLang": true
    },
    "wrap": {
      "Locales": [],
      "Type": "WrapDeformer",
      "Version": 231025828,
      "CanNotHaveX64": true,
      "CanNotHaveLang": true
    },
    "sfur": {
      "Locales": [],
      "Type": "ShellFur",
      "Version": 5,
      "CanNotHaveX64": true,
      "CanNotHaveLang": true
    },
    "cfil": {
      "Locales": [],
      "Type": "CollisionFilter",
      "Version": 7,
      "CanNotHaveX64": true,
      "CanNotHaveLang": true
    },
    "cmat": {
      "Locales": [],
      "Type": "CollisionMaterial",
      "Version": 3,
      "CanNotHaveX64": true,
      "CanNotHaveLang": true
    },
    "cdef": {
      "Locales": [],
      "Type": "CollisionDefinition",
      "Version": 7,
      "CanNotHaveX64": true,
      "CanNotHaveLang": true
    },
    "finf": {
      "Locales": [],
      "Type": "FilterInfo",
      "Version": 2,
      "CanNotHaveX64": true,
      "CanNotHaveLang": true
    },
    "def": {
      "Locales": [],
      "Type": "DynamicsDefinition",
      "Version": 6,
      "CanNotHaveX64": true,
      "CanNotHaveLang": true
    },
    "gcp": {
      "Locales": [],
      "Type": "GUIColorPreset",
      "Version": 2,
      "CanNotHaveX64": true,
      "CanNotHaveLang": true
    },
    "gsty": {
      "Locales": [],
      "Type": "GUIStyleList",
      "Version": 4,
      "CanNotHaveX64": true,
      "CanNotHaveLang": true
    },
    "gcf": {
      "Locales": [],
      "Type": "GUIConfig",
      "Version": 27,
      "CanHaveX64": true,
      "CanNotHaveX64": true,
      "CanNotHaveLang": true
    },
    "rcf": {
      "Locales": [],
      "Type": "RagdollController",
      "Version": 2,
      "CanNotHaveX64": true,
      "CanNotHaveLang": true
    },
    "rtmr": {
      "Locales": [],
      "Type": "RayTraceMaterialRedirect",
      "Version": 6,
      "CanNotHaveX64": true,
      "CanNotHaveLang": true
    },
    "sss": {
      "Locales": [],
      "Type": "SSSProfile",
      "Version": 4,
      "CanNotHaveX64": true,
      "CanNotHaveLang": true
    },
    "lod": {
      "Locales": [],
      "Type": "Lod",
      "Version": 3,
      "CanNotHaveX64": true,
      "CanNotHaveLang": true
    },
    "terr": {
      "Locales": [],
      "Type": "Terrain",
      "Version": 24008,
      "CanNotHaveX64": true,
      "CanNotHaveLang": true
    },
    "hf": {
      "Locales": [],
      "Type": "HeightField",
      "Version": 4,
      "CanNotHaveX64": true,
      "CanNotHaveLang": true
    },
    "chf": {
      "Locales": [],
      "Type": "CollisionHeightField",
      "Version": 2,
      "CanNotHaveX64": true,
      "CanNotHaveLang": true
    },
    "gml": {
      "Locales": [],
      "Type": "GroundMaterialList",
      "Version": 858718217,
      "CanNotHaveX64": true,
      "CanNotHaveLang": true
    },
    "gtl": {
      "Locales": [],
      "Type": "GroundTextureList",
      "Version": 858718223,
      "CanNotHaveX64": true,
      "CanNotHaveLang": true
    },
    "grnd": {
      "Locales": [],
      "Type": "Ground",
      "Version": 858720015,
      "CanNotHaveX64": true,
      "CanNotHaveLang": true
    },
    "stmesh": {
      "Locales": [],
      "Type": "SpeedTreeMesh",
      "Version": 231011879,
      "CanNotHaveX64": true,
      "CanNotHaveLang": true
    },
    "abcmesh": {
      "Locales": [],
      "Type": "AlembicMesh",
      "Version": 12,
      "CanNotHaveX64": true,
      "CanNotHaveLang": true
    },
    "mcamlist": {
      "Locales": [],
      "Type": "MotionCameraList",
      "Version": 22,
      "CanNotHaveX64": true,
      "CanNotHaveLang": true
    },
    "tmlfsm2": {
      "Locales": [],
      "Type": "TimelineFsm2",
      "Version": 41062003,
      "CanNotHaveX64": true,
      "CanNotHaveLang": true
    },
    "uvs": {
      "Locales": [],
      "Type": "UVSequence",
      "Version": 8,
      "CanHaveX64": true,
      "CanNotHaveX64": true,
      "CanNotHaveLang": true
    },
    "efx": {
      "Locales": [],
      "Type": "Effect",
      "Version": 4064419,
      "CanNotHaveX64": true,
      "CanNotHaveLang": true
    },
    "gui": {
      "Locales": [
        "ar",
        "ja"
      ],
      "Type": "GUI",
      "Version": 620035,
      "CanNotHaveX64": true,
      "CanHaveLang": true,
      "CanNotHaveLang": true
    },
    "oft": {
      "Locales": [],
      "Type": "OutlineFont",
      "Version": 1,
      "CanNotHaveX64": true,
      "CanNotHaveLang": true
    },
    "fslt": {
      "Locales": [],
      "Type": "FontSlot",
      "Version": 4,
      "CanNotHaveX64": true,
      "CanNotHaveLang": true
    },
    "ift": {
      "Locales": [],
      "Type": "IconFont",
      "Version": 7,
      "CanNotHaveX64": true,
      "CanNotHaveLang": true
    },
    "ocioc": {
      "Locales": [],
      "Type": "OpenColorIOConfig",
      "Version": 1000342933,
      "CanNotHaveX64": true,
      "CanNotHaveLang": true
    },
    "star": {
      "Locales": [],
      "Type": "StarCatalogue",
      "Version": 3,
      "CanNotHaveX64": true,
      "CanNotHaveLang": true
    },
    "msg": {
      "Locales": [],
      "Type": "Message",
      "Version": 22,
      "CanNotHaveX64": true,
      "CanNotHaveLang": true
    },
    "mov": {
      "Locales": [],
      "Type": "Movie",
      "Version": 1,
      "CanHaveX64": true,
      "CanNotHaveX64": true,
      "CanNotHaveLang": true
    },
    "aimapattr": {
      "Locales": [],
      "Type": "AIMapAttribute",
      "Version": 46,
      "CanNotHaveX64": true,
      "CanNotHaveLang": true
    },
    "ainvmmgr": {
      "Locales": [],
      "Type": "AIMap",
      "Version": 8,
      "CanNotHaveX64": true,
      "CanNotHaveLang": true
    },
    "aiwaypmgr": {
      "Locales": [],
      "Type": "AIMap",
      "Version": 8,
      "CanNotHaveX64": true,
      "CanNotHaveLang": true
    },
    "swms": {
      "Locales": [],
      "Type": "MemorySettings",
      "Version": 1,
      "CanNotHaveX64": true,
      "CanNotHaveLang": true
    },
    "sbnk": {
      "Locales": [
        "en",
        "ja"
      ],
      "Type": "SoundBank",
      "Version": 1,
      "CanHaveX64": true,
      "CanHaveLang": true,
      "CanNotHaveLang": true
    },
    "spck": {
      "Locales": [
        "en",
        "ja"
      ],
      "Type": "SoundPackage",
      "Version": 1,
      "CanHaveX64": true,
      "CanHaveLang": true,
      "CanNotHaveLang": true
    },
    "sdf": {
      "Locales": [
        "stm"
      ],
      "Type": "sdf",
      "Version": 240112003,
      "CanNotHaveX64": true,
      "CanHaveLang": true,
      "CanNotHaveLang": true
    },
    "lprb": {
      "Locales": [],
      "Type": "LightProbes",
      "Version": 6,
      "CanNotHaveX64": true,
      "CanNotHaveLang": true
    },
    "prb": {
      "Locales": [],
      "Type": "Probes",
      "Version": 9,
      "CanNotHaveX64": true,
      "CanNotHaveLang": true
    },
    "rcfg": {
      "Locales": [],
      "Type": "rcfg",
      "Version": 10,
      "CanNotHaveX64": true,
      "CanNotHaveLang": true
    },
    "vsdf": {
      "Locales": [],
      "Type": "VfxShader",
      "Version": 240112006,
      "CanNotHaveX64": true,
      "CanNotHaveLang": true
    },
    "vsdflist": {
      "Locales": [],
      "Type": "VfxShaderList",
      "Version": 1,
      "CanNotHaveX64": true,
      "CanNotHaveLang": true
    },
    "efcsv": {
      "Locales": [],
      "Type": "EffectCsv",
      "Version": 1,
      "CanNotHaveX64": true,
      "CanNotHaveLang": true
    },
    "tml": {
      "Locales": [],
      "Type": "Timeline",
      "Version": 62002,
      "CanNotHaveX64": true,
      "CanNotHaveLang": true
    },
    "lfa": {
      "Locales": [],
      "Type": "Lensflare",
      "Version": 4,
      "CanNotHaveX64": true,
      "CanNotHaveLang": true
    },
    "fxct": {
      "Locales": [],
      "Type": "fxct",
      "Version": 4,
      "CanNotHaveX64": true,
      "CanNotHaveLang": true
    },
    "eem": {
      "Locales": [],
      "Type": "EffectEmitMask",
      "CanNotHaveX64": true,
      "CanNotHaveLang": true
    }
  }
}